tfextras/__init__.py
tfextras/device.py
tfextras/graph.py
tfextras/io.py
tfextras/ops.py
tfextras/params.py
tfextras/train.py
tfextras-0.0.13.dist-info/METADATA
tfextras-0.0.13.dist-info/RECORD
tfextras-0.0.13.dist-info/WHEEL
tfextras-0.0.13.dist-info/top_level.txt
